ippd/__init__.py
ippd/__main__.py
InstagramProfilePhotosDownloader-0.1.3.dist-info/METADATA
InstagramProfilePhotosDownloader-0.1.3.dist-info/WHEEL
InstagramProfilePhotosDownloader-0.1.3.dist-info/entry_points.txt
InstagramProfilePhotosDownloader-0.1.3.dist-info/top_level.txt
InstagramProfilePhotosDownloader-0.1.3.dist-info/RECORD
