Metadata-Version: 2.1
Name: InstagramProfilePhotosDownloader
Version: 0.1.3
Summary: A simple scraping tool to download an Instagram profile photos.
Home-page: https://github.com/massimopavoni/InstagramProfilePhotosDownloader
Author: Massimo Pavoni
Author-email: maspavoni@gmail.com
Platform: OS Independent
Classifier: License :: OSI Approved :: GNU General Public License v3 (GPLv3)
Classifier: Programming Language :: Python
Classifier: Operating System :: OS Independent
Requires-Python: >=3.11
Requires-Dist: selenium >=4.7
Requires-Dist: requests >=2.28
